tree_influence/__init__.py
tree_influence/classes.py
tree_influence/explainers/__init__.py
tree_influence/explainers/base.py
tree_influence/explainers/boostin.py
tree_influence/explainers/boostinLE.py
tree_influence/explainers/boostinW1.py
tree_influence/explainers/boostinW1LE.py
tree_influence/explainers/boostinW2.py
tree_influence/explainers/boostinW2LE.py
tree_influence/explainers/dshap.py
tree_influence/explainers/input_sim.py
tree_influence/explainers/leaf_inf.py
tree_influence/explainers/leaf_infLE.py
tree_influence/explainers/leaf_infSP.py
tree_influence/explainers/leaf_infSPLE.py
tree_influence/explainers/leaf_refit.py
tree_influence/explainers/leaf_refitLE.py
tree_influence/explainers/leaf_sim.py
tree_influence/explainers/loo.py
tree_influence/explainers/looLE.py
tree_influence/explainers/loss.py
tree_influence/explainers/minority.py
tree_influence/explainers/random.py
tree_influence/explainers/subsample.py
tree_influence/explainers/target.py
tree_influence/explainers/tree_sim.py
tree_influence/explainers/trex.py
tree_influence/explainers/parsers/__init__.py
tree_influence/explainers/parsers/_tree32.c
tree_influence/explainers/parsers/_tree32.cp39-win_amd64.pyd
tree_influence/explainers/parsers/_tree64.c
tree_influence/explainers/parsers/_tree64.cp39-win_amd64.pyd
tree_influence/explainers/parsers/parser_cb.py
tree_influence/explainers/parsers/parser_lgb.py
tree_influence/explainers/parsers/parser_sk.py
tree_influence/explainers/parsers/parser_xgb.py
tree_influence/explainers/parsers/setup.py
tree_influence/explainers/parsers/tree.py
tree_influence/explainers/parsers/util.py
tree_influence-0.1.7.dist-info/LICENSE
tree_influence-0.1.7.dist-info/METADATA
tree_influence-0.1.7.dist-info/WHEEL
tree_influence-0.1.7.dist-info/top_level.txt
tree_influence-0.1.7.dist-info/RECORD
