Metadata-Version: 2.1
Name: tree-influence
Version: 0.1.7
Summary: Influence Estimation for Gradient-Boosted Decision Trees
Home-page: https://github.com/jjbrophy47/tree_influence
Author: Jonathan Brophy
Author-email: jonathanbrophy47@gmail.com
Classifier: Programming Language :: Python :: 3.9
Classifier: Programming Language :: Python :: 3.10
Classifier: License :: OSI Approved :: Apache Software License
Classifier: Operating System :: OS Independent
Requires-Python: >=3.9
License-File: LICENSE
Requires-Dist: numpy>=1.22
Requires-Dist: scikit-learn>=0.24.2
Requires-Dist: torch>=1.9.0
